explaidllm/__init__.py
explaidllm/__main__.py
explaidllm/cli/__init__.py
explaidllm/cli/clingo_app.py
explaidllm/cli/rendering.py
explaidllm/llms/__init__.py
explaidllm/llms/models/__init__.py
explaidllm/llms/models/base.py
explaidllm/llms/models/openai.py
explaidllm/llms/models/tags.py
explaidllm/llms/templates/__init__.py
explaidllm/llms/templates/base.py
explaidllm/llms/templates/explain.py
explaidllm/llms/templates/prompt_templates/explain_input.txt
explaidllm/llms/templates/prompt_templates/explain_instructions.txt
explaidllm/spinner/__init__.py
explaidllm/utils/__init__.py
explaidllm/utils/logging.py
explaidllm-0.1.5.dist-info/licenses/LICENSE
explaidllm-0.1.5.dist-info/METADATA
explaidllm-0.1.5.dist-info/WHEEL
explaidllm-0.1.5.dist-info/entry_points.txt
explaidllm-0.1.5.dist-info/top_level.txt
explaidllm-0.1.5.dist-info/RECORD
