Metadata-Version: 2.4
Name: explaidllm
Version: 0.1.5
Summary: CLI tool for debugging clingo using a combination of MUS and LLMs
Author-email: Hannes Weichelt <hweichelt@uni-potsdam.de>
Maintainer-email: Hannes Weichelt <hweichelt@uni-potsdam.de>
License: MIT License
Project-URL: Homepage, https://github.com/hweichelt/explaidllm
Project-URL: Source, https://github.com/hweichelt/explaidllm
Project-URL: Issues, https://github.com/hweichelt/explaidllm/issues
Classifier: Development Status :: 4 - Beta
Classifier: Environment :: Console
Classifier: Intended Audience :: Developers
Classifier: License :: OSI Approved :: MIT License
Classifier: Programming Language :: Python :: 3
Classifier: Programming Language :: Python :: 3 :: Only
Classifier: Programming Language :: Python :: 3.12
Classifier: Operating System :: OS Independent
Classifier: Topic :: Software Development :: Libraries :: Python Modules
Classifier: Typing :: Typed
Requires-Python: >=3.12
License-File: LICENSE
Requires-Dist: clingo>=5.8
Requires-Dist: clingexplaid>=1.3.5
Requires-Dist: openai>=1.107
Requires-Dist: python-dotenv>=1.1.1
Requires-Dist: cursor==1.3.5
Requires-Dist: autoflake
Dynamic: license-file
